agent_zero/__init__.py
agent_zero/database_logger.py
agent_zero/main.py
agent_zero/mcp_env.py
agent_zero/mcp_server.py
agent_zero/mcp_tracer.py
agent_zero/monitoring_endpoints.py
agent_zero/py.typed
agent_zero/query_metrics.py
agent_zero/server_config.py
agent_zero/utils.py
agent_zero/monitoring/__init__.py
agent_zero/monitoring/error_analysis.py
agent_zero/monitoring/insert_operations.py
agent_zero/monitoring/parts_merges.py
agent_zero/monitoring/query_performance.py
agent_zero/monitoring/resource_usage.py
agent_zero/monitoring/system_components.py
agent_zero/monitoring/table_statistics.py
agent_zero/monitoring/utility.py
build/lib/agent_zero/__init__.py
build/lib/agent_zero/database_logger.py
build/lib/agent_zero/main.py
build/lib/agent_zero/mcp_env.py
build/lib/agent_zero/mcp_server.py
build/lib/agent_zero/mcp_tracer.py
build/lib/agent_zero/monitoring_endpoints.py
build/lib/agent_zero/py.typed
build/lib/agent_zero/query_metrics.py
build/lib/agent_zero/server_config.py
build/lib/agent_zero/utils.py
build/lib/agent_zero/monitoring/__init__.py
build/lib/agent_zero/monitoring/error_analysis.py
build/lib/agent_zero/monitoring/insert_operations.py
build/lib/agent_zero/monitoring/parts_merges.py
build/lib/agent_zero/monitoring/query_performance.py
build/lib/agent_zero/monitoring/resource_usage.py
build/lib/agent_zero/monitoring/system_components.py
build/lib/agent_zero/monitoring/table_statistics.py
build/lib/agent_zero/monitoring/utility.py
build/lib/build/lib/agent_zero/__init__.py
build/lib/build/lib/agent_zero/database_logger.py
build/lib/build/lib/agent_zero/main.py
build/lib/build/lib/agent_zero/mcp_env.py
build/lib/build/lib/agent_zero/mcp_server.py
build/lib/build/lib/agent_zero/mcp_tracer.py
build/lib/build/lib/agent_zero/monitoring_endpoints.py
build/lib/build/lib/agent_zero/py.typed
build/lib/build/lib/agent_zero/query_metrics.py
build/lib/build/lib/agent_zero/server_config.py
build/lib/build/lib/agent_zero/utils.py
ch_agent_zero-0.0.0.dist-info/licenses/LICENSE
ch_agent_zero-0.0.0.dist-info/METADATA
ch_agent_zero-0.0.0.dist-info/WHEEL
ch_agent_zero-0.0.0.dist-info/entry_points.txt
ch_agent_zero-0.0.0.dist-info/top_level.txt
ch_agent_zero-0.0.0.dist-info/RECORD
