Metadata-Version: 2.4
Name: ch_agent_zero
Version: 0.0.0
Summary: Model Context Protocol (MCP) server for monitoring, analyzing, and managing ClickHouse databases
Author-email: Maruthi Prithivi <maruthiprithivi@gmail.com>
License-Expression: Apache-2.0
Project-URL: Homepage, https://github.com/maruthiprithivi/agent_zero
Project-URL: Documentation, https://github.com/maruthiprithivi/agent_zero/blob/main/README.md
Project-URL: Bug Tracker, https://github.com/maruthiprithivi/agent_zero/issues
Requires-Python: >=3.13
License-File: LICENSE
Requires-Dist: aiohttp>=3.11.14
Requires-Dist: build>=1.2.2.post1
Requires-Dist: clickhouse-connect>=0.8.15
Requires-Dist: fastapi>=0.115.12
Requires-Dist: mcp[cli]>=1.4.1
Requires-Dist: pkginfo>=1.12.1.2
Requires-Dist: pre-commit>=4.2.0
Requires-Dist: prometheus-client>=0.21.1
Requires-Dist: pydantic>=2.10.6
Requires-Dist: python-dotenv>=1.0.1
Requires-Dist: structlog>=25.2.0
Requires-Dist: tenacity>=9.0.0
Requires-Dist: twine>=6.1.0
Requires-Dist: uvicorn>=0.34.0
Requires-Dist: wheel>=0.45.1
Dynamic: license-file
